DodayUtils/DodayInventory.py
DodayUtils/DodayPeripherals.py
DodayUtils/DodayUtilManager.py
DodayUtils/DodayWebsocket.py
DodayUtils/OrderInfo.py
DodayUtils/__init__.py
DodayUtils/_dwrappers.py
DodayUtils/_exceptions.py
DodayUtils/_helpers.py
DodayUtils/assets/DodayAsset.py
DodayUtils/assets/DodayAssetLog.py
DodayUtils/assets/DodayAssetRequest.py
DodayUtils/assets/__init__.py
DodayUtils/clienttools/DodayWebsocketClient.py
DodayUtils/clienttools/ImgQTClient.py
DodayUtils/clienttools/ZMQClient.py
DodayUtils/clienttools/__init__.py
DodayUtils/formats/DodayInventorySticker.py
DodayUtils/formats/DodayNanshanInvoice.py
DodayUtils/formats/DodayOrderSticker.py
DodayUtils/formats/DodayRawInvoice.py
DodayUtils/formats/OnlineInvoice.py
DodayUtils/formats/_Barcode.py
DodayUtils/formats/_Basic.py
DodayUtils/formats/_Graphic.py
DodayUtils/formats/_QRCode.py
DodayUtils/formats/__init__.py
DodayUtils/formats/font/msyh.ttf
DodayUtils/member/MemberInfo.py
DodayUtils/member/__init__.py
DodayUtils/menu/MenuInfo.py
DodayUtils/menu/MenuUtils.py
DodayUtils/menu/__init__.py
DodayUtils/order/DodayItem.py
DodayUtils/order/MultiOrderSummary.py
DodayUtils/order/OrderInfo.py
DodayUtils/order/__init__.py
DodayUtils/payment/Cash.py
DodayUtils/payment/DodayPayment.py
DodayUtils/payment/IntegratedEPay.py
DodayUtils/payment/LinePay.py
DodayUtils/payment/__init__.py
DodayUtils/peripherals/CliTools.py
DodayUtils/peripherals/DodayApiLib.py
DodayUtils/peripherals/DodayCam.py
DodayUtils/peripherals/PrinterTools.py
DodayUtils/peripherals/__init__.py
DodayUtils/peripherals/defaults/ding.mp3
DodayUtils/peripherals/defaults/libdoday_api.so
DodayUtils/promotion/PromotionEffector.py
DodayUtils/promotion/PromotionInfo.py
DodayUtils/promotion/__init__.py
DodayUtils/tests/__init__.py
DodayUtils/tests/test_order_info.py
DodayUtils/tests/test_promotion_info.py
DodayUtils-0.4.2.dist-info/METADATA
DodayUtils-0.4.2.dist-info/WHEEL
DodayUtils-0.4.2.dist-info/top_level.txt
DodayUtils-0.4.2.dist-info/RECORD
