Metadata-Version: 2.1
Name: DodayUtils
Version: 0.4.2
Summary: Doday Utility Package
Home-page: UNKNOWN
Author: Gadgethi Develop Team
Author-email: developers@gadget-hitech.com
License: AGPLv3+
Platform: UNKNOWN
Classifier: Intended Audience :: Developers
Classifier: License :: OSI Approved :: GNU Affero General Public License v3 or later (AGPLv3+)
Classifier: Programming Language :: Python :: 3.5
Classifier: Programming Language :: Python :: 3.6
Classifier: Programming Language :: Python :: 3.7
Classifier: Operating System :: OS Independent
Classifier: Topic :: Software Development :: Libraries 
Requires-Python: >=3.5
Requires-Dist: gadgethiServerUtils (>=0.3.14)
Requires-Dist: websocket-client
Requires-Dist: qrcode
Requires-Dist: Pillow
